{"includedArchiveIdentifiers":["EudiWalletKit"],"interfaceLanguages":{"swift":[{"children":[{"title":"Essentials","type":"groupMarker"},{"path":"\/documentation\/eudiwalletkit\/getstarted","title":"Get started","type":"article"},{"path":"\/documentation\/eudiwalletkit\/managedocuments","title":"Manage documents","type":"article"},{"path":"\/documentation\/eudiwalletkit\/issuedocuments","title":"Issue documents","type":"article"},{"path":"\/documentation\/eudiwalletkit\/secureareas","title":"Custom key management","type":"article"},{"path":"\/documentation\/eudiwalletkit\/presentationservice","title":"Presentation Service","type":"article"},{"path":"\/documentation\/eudiwalletkit\/walletui","title":"EUDI iOS Wallet reference implementation","type":"sampleCode"},{"title":"Classes","type":"groupMarker"},{"children":[{"title":"Initializers","type":"groupMarker"},{"path":"\/documentation\/eudiwalletkit\/blepresentationservice\/init(parameters:)","title":"init(parameters: InitializeTransferData) throws","type":"init"},{"title":"Instance Properties","type":"groupMarker"},{"path":"\/documentation\/eudiwalletkit\/blepresentationservice\/flow","title":"var flow: FlowType","type":"property"},{"path":"\/documentation\/eudiwalletkit\/blepresentationservice\/status","title":"var status: TransferStatus","type":"property"},{"title":"Instance Methods","type":"groupMarker"},{"path":"\/documentation\/eudiwalletkit\/blepresentationservice\/receiverequest()","title":"func receiveRequest() async throws -> UserRequestInfo","type":"method"},{"path":"\/documentation\/eudiwalletkit\/blepresentationservice\/sendresponse(useraccepted:itemstosend:onsuccess:)","title":"func sendResponse(userAccepted: Bool, itemsToSend: RequestItems, onSuccess: ((URL?) -> Void)?) async throws","type":"method"},{"path":"\/documentation\/eudiwalletkit\/blepresentationservice\/startqrengagement(secureareaname:crv:)","title":"func startQrEngagement(secureAreaName: String?, crv: CoseEcCurve) async throws -> String","type":"method"},{"path":"\/documentation\/eudiwalletkit\/blepresentationservice\/unlockkey(id:)","title":"func unlockKey(id: String) async throws -> Data?","type":"method"},{"title":"Default Implementations","type":"groupMarker"},{"children":[{"title":"Instance Methods","type":"groupMarker"},{"path":"\/documentation\/eudiwalletkit\/blepresentationservice\/didchangestatus(_:)","title":"func didChangeStatus(TransferStatus)","type":"method"},{"path":"\/documentation\/eudiwalletkit\/blepresentationservice\/didfinishedwitherror(_:)","title":"func didFinishedWithError(any Error)","type":"method"},{"path":"\/documentation\/eudiwalletkit\/blepresentationservice\/didreceiverequest(_:handleselected:)","title":"func didReceiveRequest(UserRequestInfo, handleSelected: (Bool, RequestItems?) async -> Void)","type":"method"}],"path":"\/documentation\/eudiwalletkit\/blepresentationservice\/mdocofflinedelegate-implementations","title":"MdocOfflineDelegate Implementations","type":"symbol"}],"path":"\/documentation\/eudiwalletkit\/blepresentationservice","title":"BlePresentationService","type":"class"},{"children":[{"title":"Initializers","type":"groupMarker"},{"path":"\/documentation\/eudiwalletkit\/eudiwallet\/init(storagetype:servicename:accessgroup:trustedreadercertificates:userauthenticationrequired:verifierapiuri:openid4vciissuerurl:openid4vciconfig:urlsession:logfilename:secureareas:modelfactory:)","title":"init(storageType: StorageType, serviceName: String?, accessGroup: String?, trustedReaderCertificates: [Data]?, userAuthenticationRequired: Bool, verifierApiUri: String?, openID4VciIssuerUrl: String?, openID4VciConfig: OpenId4VCIConfig?, urlSession: URLSession?, logFileName: String?, secureAreas: [any SecureArea]?, modelFactory: (any DocClaimsDecodableFactory)?) throws","type":"init"},{"title":"Instance Properties","type":"groupMarker"},{"path":"\/documentation\/eudiwalletkit\/eudiwallet\/accessgroup","title":"var accessGroup: String?","type":"property"},{"path":"\/documentation\/eudiwalletkit\/eudiwallet\/deviceauthmethod","title":"var deviceAuthMethod: DeviceAuthMethod","type":"property"},{"path":"\/documentation\/eudiwalletkit\/eudiwallet\/logfilename","title":"var logFileName: String?","type":"property"},{"path":"\/documentation\/eudiwalletkit\/eudiwallet\/modelfactory","title":"var modelFactory: (any DocClaimsDecodableFactory)?","type":"property"},{"path":"\/documentation\/eudiwalletkit\/eudiwallet\/openid4vciconfig","title":"var openID4VciConfig: OpenId4VCIConfig?","type":"property"},{"path":"\/documentation\/eudiwalletkit\/eudiwallet\/openid4vciissuerurl","title":"var openID4VciIssuerUrl: String?","type":"property"},{"path":"\/documentation\/eudiwalletkit\/eudiwallet\/servicename","title":"var serviceName: String","type":"property"},{"path":"\/documentation\/eudiwalletkit\/eudiwallet\/storage","title":"var storage: StorageManager!","type":"property"},{"path":"\/documentation\/eudiwalletkit\/eudiwallet\/trustedreadercertificates","title":"var trustedReaderCertificates: [Data]?","type":"property"},{"path":"\/documentation\/eudiwalletkit\/eudiwallet\/uiculture","title":"var uiCulture: String?","type":"property"},{"path":"\/documentation\/eudiwalletkit\/eudiwallet\/urlsession","title":"var urlSession: URLSession","type":"property"},{"path":"\/documentation\/eudiwalletkit\/eudiwallet\/userauthenticationrequired","title":"var userAuthenticationRequired: Bool","type":"property"},{"path":"\/documentation\/eudiwalletkit\/eudiwallet\/verifierapiuri","title":"var verifierApiUri: String?","type":"property"},{"path":"\/documentation\/eudiwalletkit\/eudiwallet\/verifierlegalname","title":"var verifierLegalName: String?","type":"property"},{"title":"Instance Methods","type":"groupMarker"},{"path":"\/documentation\/eudiwalletkit\/eudiwallet\/beginissuedocument(id:keyoptions:bdeferred:)","title":"func beginIssueDocument(id: String, keyOptions: KeyOptions?, bDeferred: Bool) async throws -> IssueRequest","type":"method"},{"path":"\/documentation\/eudiwalletkit\/eudiwallet\/beginpresentation(flow:doctype:)","title":"func beginPresentation(flow: FlowType, docType: String?) async -> PresentationSession","type":"method"},{"path":"\/documentation\/eudiwalletkit\/eudiwallet\/beginpresentation(service:)","title":"func beginPresentation(service: any PresentationService) async -> PresentationSession","type":"method"},{"path":"\/documentation\/eudiwalletkit\/eudiwallet\/deletealldocuments()","title":"func deleteAllDocuments() async throws","type":"method"},{"path":"\/documentation\/eudiwalletkit\/eudiwallet\/deletedocument(id:status:)","title":"func deleteDocument(id: String, status: DocumentStatus) async throws","type":"method"},{"path":"\/documentation\/eudiwalletkit\/eudiwallet\/deletedocuments(status:)","title":"func deleteDocuments(status: DocumentStatus) async throws","type":"method"},{"path":"\/documentation\/eudiwalletkit\/eudiwallet\/endissuedocument(_:)","title":"func endIssueDocument(Document) async throws","type":"method"},{"path":"\/documentation\/eudiwalletkit\/eudiwallet\/getissuermetadata()","title":"func getIssuerMetadata() async throws -> CredentialIssuerMetadata","type":"method"},{"path":"\/documentation\/eudiwalletkit\/eudiwallet\/getlogfilecontents(_:)","title":"func getLogFileContents(String) throws -> String","type":"method"},{"path":"\/documentation\/eudiwalletkit\/eudiwallet\/issuedocument(doctype:scope:identifier:keyoptions:promptmessage:)","title":"func issueDocument(docType: String?, scope: String?, identifier: String?, keyOptions: KeyOptions?, promptMessage: String?) async throws -> Document","type":"method"},{"path":"\/documentation\/eudiwalletkit\/eudiwallet\/issuedocumentsbyofferurl(offeruri:doctypes:doctypekeyoptions:txcodevalue:promptmessage:claimset:)","title":"func issueDocumentsByOfferUrl(offerUri: String, docTypes: [OfferedDocModel], docTypeKeyOptions: [String : KeyOptions]?, txCodeValue: String?, promptMessage: String?, claimSet: ClaimSet?) async throws -> [Document]","type":"method"},{"path":"\/documentation\/eudiwalletkit\/eudiwallet\/loadalldocuments()","title":"func loadAllDocuments() async throws -> [Document]?","type":"method"},{"path":"\/documentation\/eudiwalletkit\/eudiwallet\/loaddocument(id:status:)","title":"func loadDocument(id: String, status: DocumentStatus) async throws -> Document?","type":"method"},{"path":"\/documentation\/eudiwalletkit\/eudiwallet\/loaddocuments(status:)","title":"func loadDocuments(status: DocumentStatus) async throws -> [Document]?","type":"method"},{"path":"\/documentation\/eudiwalletkit\/eudiwallet\/loadsampledata(sampledatafiles:)","title":"func loadSampleData(sampleDataFiles: [String]?) async throws","type":"method"},{"path":"\/documentation\/eudiwalletkit\/eudiwallet\/prepareservicedataparameters(doctype:format:)","title":"func prepareServiceDataParameters(docType: String?, format: DocDataFormat?) async throws -> InitializeTransferData","type":"method"},{"path":"\/documentation\/eudiwalletkit\/eudiwallet\/requestdeferredissuance(deferreddoc:keyoptions:)","title":"func requestDeferredIssuance(deferredDoc: Document, keyOptions: KeyOptions?) async throws -> Document","type":"method"},{"path":"\/documentation\/eudiwalletkit\/eudiwallet\/resetlogfile(_:)","title":"func resetLogFile(String) throws","type":"method"},{"path":"\/documentation\/eudiwalletkit\/eudiwallet\/resolveofferurldoctypes(urioffer:)","title":"func resolveOfferUrlDocTypes(uriOffer: String) async throws -> OfferedIssuanceModel","type":"method"},{"path":"\/documentation\/eudiwalletkit\/eudiwallet\/resumependingissuance(pendingdoc:weburl:keyoptions:)","title":"func resumePendingIssuance(pendingDoc: Document, webUrl: URL?, keyOptions: KeyOptions?) async throws -> Document","type":"method"},{"title":"Type Properties","type":"groupMarker"},{"path":"\/documentation\/eudiwalletkit\/eudiwallet\/defaultclientid","title":"static let defaultClientId: String","type":"property"},{"path":"\/documentation\/eudiwalletkit\/eudiwallet\/defaultopenid4vciredirecturi","title":"static let defaultOpenID4VciRedirectUri: URL","type":"property"},{"path":"\/documentation\/eudiwalletkit\/eudiwallet\/defaultopenid4vciconfig","title":"static let defaultOpenId4VCIConfig: OpenId4VCIConfig","type":"property"},{"path":"\/documentation\/eudiwalletkit\/eudiwallet\/defaultservicename","title":"static let defaultServiceName: String","type":"property"},{"title":"Type Methods","type":"groupMarker"},{"path":"\/documentation\/eudiwalletkit\/eudiwallet\/authorizedaction(action:disabled:dismiss:localizedreason:)","title":"static func authorizedAction<T>(action: () async throws -> T, disabled: Bool, dismiss: () -> Void, localizedReason: String) async throws -> T?","type":"method"},{"path":"\/documentation\/eudiwalletkit\/eudiwallet\/getlogfileurl(_:)","title":"static func getLogFileURL(String) throws -> URL?","type":"method"},{"title":"Default Implementations","type":"groupMarker"},{"children":[{"title":"Instance Properties","type":"groupMarker"},{"path":"\/documentation\/eudiwalletkit\/eudiwallet\/objectwillchange","title":"var objectWillChange: ObservableObjectPublisher","type":"property"}],"path":"\/documentation\/eudiwalletkit\/eudiwallet\/observableobject-implementations","title":"ObservableObject Implementations","type":"symbol"}],"path":"\/documentation\/eudiwalletkit\/eudiwallet","title":"EudiWallet","type":"class"},{"children":[{"title":"Initializers","type":"groupMarker"},{"path":"\/documentation\/eudiwalletkit\/faultpresentationservice\/init(error:)","title":"init(error: any Error)","type":"init"},{"path":"\/documentation\/eudiwalletkit\/faultpresentationservice\/init(msg:)","title":"init(msg: String)","type":"init"},{"title":"Instance Properties","type":"groupMarker"},{"path":"\/documentation\/eudiwalletkit\/faultpresentationservice\/flow","title":"var flow: FlowType","type":"property"},{"path":"\/documentation\/eudiwalletkit\/faultpresentationservice\/status","title":"var status: TransferStatus","type":"property"},{"title":"Instance Methods","type":"groupMarker"},{"path":"\/documentation\/eudiwalletkit\/faultpresentationservice\/receiverequest()","title":"func receiveRequest() async throws -> UserRequestInfo","type":"method"},{"path":"\/documentation\/eudiwalletkit\/faultpresentationservice\/sendresponse(useraccepted:itemstosend:onsuccess:)","title":"func sendResponse(userAccepted: Bool, itemsToSend: RequestItems, onSuccess: ((URL?) -> Void)?) async throws","type":"method"},{"path":"\/documentation\/eudiwalletkit\/faultpresentationservice\/startqrengagement(secureareaname:crv:)","title":"func startQrEngagement(secureAreaName: String?, crv: CoseEcCurve) async throws -> String","type":"method"}],"path":"\/documentation\/eudiwalletkit\/faultpresentationservice","title":"FaultPresentationService","type":"class"},{"children":[{"title":"Instance Methods","type":"groupMarker"},{"path":"\/documentation\/eudiwalletkit\/openid4vciservice\/presentationanchor(for:)","title":"func presentationAnchor(for: ASWebAuthenticationSession) -> ASPresentationAnchor","type":"method"},{"path":"\/documentation\/eudiwalletkit\/openid4vciservice\/resolveofferdoctypes(urioffer:)","title":"func resolveOfferDocTypes(uriOffer: String) async throws -> OfferedIssuanceModel","type":"method"}],"path":"\/documentation\/eudiwalletkit\/openid4vciservice","title":"OpenId4VCIService","type":"class"},{"children":[{"title":"Initializers","type":"groupMarker"},{"path":"\/documentation\/eudiwalletkit\/openid4vpservice\/init(parameters:qrcode:openid4vpverifierapiuri:openid4vpverifierlegalname:urlsession:)","title":"init(parameters: InitializeTransferData, qrCode: Data, openId4VpVerifierApiUri: String?, openId4VpVerifierLegalName: String?, urlSession: URLSession) throws","type":"init"},{"title":"Instance Properties","type":"groupMarker"},{"path":"\/documentation\/eudiwalletkit\/openid4vpservice\/flow","title":"var flow: FlowType","type":"property"},{"path":"\/documentation\/eudiwalletkit\/openid4vpservice\/status","title":"var status: TransferStatus","type":"property"},{"title":"Instance Methods","type":"groupMarker"},{"path":"\/documentation\/eudiwalletkit\/openid4vpservice\/receiverequest()","title":"func receiveRequest() async throws -> UserRequestInfo","type":"method"},{"path":"\/documentation\/eudiwalletkit\/openid4vpservice\/sendresponse(useraccepted:itemstosend:onsuccess:)","title":"func sendResponse(userAccepted: Bool, itemsToSend: RequestItems, onSuccess: ((URL?) -> Void)?) async throws","type":"method"},{"path":"\/documentation\/eudiwalletkit\/openid4vpservice\/startqrengagement(secureareaname:crv:)","title":"func startQrEngagement(secureAreaName: String?, crv: CoseEcCurve) async throws -> String","type":"method"}],"path":"\/documentation\/eudiwalletkit\/openid4vpservice","title":"OpenId4VpService","type":"class"},{"children":[{"title":"Initializers","type":"groupMarker"},{"path":"\/documentation\/eudiwalletkit\/presentationsession\/init(presentationservice:docidandtypes:userauthenticationrequired:)","title":"init(presentationService: any PresentationService, docIdAndTypes: [String : (String, DocDataFormat, String?)], userAuthenticationRequired: Bool)","type":"init"},{"title":"Instance Properties","type":"groupMarker"},{"path":"\/documentation\/eudiwalletkit\/presentationsession\/deviceengagement","title":"var deviceEngagement: String?","type":"property"},{"path":"\/documentation\/eudiwalletkit\/presentationsession\/discloseddocuments","title":"var disclosedDocuments: [DocElementsViewModel]","type":"property"},{"path":"\/documentation\/eudiwalletkit\/presentationsession\/docidandtypes","title":"var docIdAndTypes: [String : (String, DocDataFormat, String?)]","type":"property"},{"path":"\/documentation\/eudiwalletkit\/presentationsession\/presentationservice","title":"var presentationService: any PresentationService","type":"property"},{"path":"\/documentation\/eudiwalletkit\/presentationsession\/readercertissuer","title":"var readerCertIssuer: String?","type":"property"},{"path":"\/documentation\/eudiwalletkit\/presentationsession\/readercertissuervalid","title":"var readerCertIssuerValid: Bool?","type":"property"},{"path":"\/documentation\/eudiwalletkit\/presentationsession\/readercertvalidationmessage","title":"var readerCertValidationMessage: String?","type":"property"},{"path":"\/documentation\/eudiwalletkit\/presentationsession\/readerlegalname","title":"var readerLegalName: String?","type":"property"},{"path":"\/documentation\/eudiwalletkit\/presentationsession\/status","title":"var status: TransferStatus","type":"property"},{"path":"\/documentation\/eudiwalletkit\/presentationsession\/uierror","title":"var uiError: WalletError?","type":"property"},{"title":"Instance Methods","type":"groupMarker"},{"path":"\/documentation\/eudiwalletkit\/presentationsession\/receiverequest()","title":"func receiveRequest() async -> UserRequestInfo?","type":"method"},{"path":"\/documentation\/eudiwalletkit\/presentationsession\/sendresponse(useraccepted:itemstosend:oncancel:onsuccess:)","title":"func sendResponse(userAccepted: Bool, itemsToSend: RequestItems, onCancel: (() -> Void)?, onSuccess: ((URL?) -> Void)?) async","type":"method"},{"path":"\/documentation\/eudiwalletkit\/presentationsession\/startqrengagement()","title":"func startQrEngagement() async","type":"method"},{"title":"Type Methods","type":"groupMarker"},{"path":"\/documentation\/eudiwalletkit\/presentationsession\/makeerror(code:str:)","title":"static func makeError(code: ErrorCode, str: String?) -> NSError","type":"method"},{"path":"\/documentation\/eudiwalletkit\/presentationsession\/makeerror(str:)","title":"static func makeError(str: String) -> NSError","type":"method"},{"title":"Default Implementations","type":"groupMarker"},{"children":[{"title":"Instance Properties","type":"groupMarker"},{"path":"\/documentation\/eudiwalletkit\/presentationsession\/objectwillchange","title":"var objectWillChange: ObservableObjectPublisher","type":"property"}],"path":"\/documentation\/eudiwalletkit\/presentationsession\/observableobject-implementations","title":"ObservableObject Implementations","type":"symbol"}],"path":"\/documentation\/eudiwalletkit\/presentationsession","title":"PresentationSession","type":"class"},{"children":[{"title":"Initializers","type":"groupMarker"},{"path":"\/documentation\/eudiwalletkit\/storagemanager\/init(storageservice:modelfactory:)","title":"init(storageService: any DataStorageService, modelFactory: (any DocClaimsDecodableFactory)?)","type":"init"},{"title":"Instance Properties","type":"groupMarker"},{"path":"\/documentation\/eudiwalletkit\/storagemanager\/deferreddocuments","title":"var deferredDocuments: [Document]","type":"property"},{"path":"\/documentation\/eudiwalletkit\/storagemanager\/doccount","title":"var docCount: Int","type":"property"},{"path":"\/documentation\/eudiwalletkit\/storagemanager\/docmodels","title":"var docModels: [any DocClaimsDecodable]","type":"property"},{"path":"\/documentation\/eudiwalletkit\/storagemanager\/hasdata","title":"var hasData: Bool","type":"property"},{"path":"\/documentation\/eudiwalletkit\/storagemanager\/pendingdocuments","title":"var pendingDocuments: [Document]","type":"property"},{"path":"\/documentation\/eudiwalletkit\/storagemanager\/uierror","title":"var uiError: WalletError?","type":"property"},{"title":"Instance Methods","type":"groupMarker"},{"path":"\/documentation\/eudiwalletkit\/storagemanager\/deletedocument(id:status:)","title":"func deleteDocument(id: String, status: DocumentStatus) async throws","type":"method"},{"path":"\/documentation\/eudiwalletkit\/storagemanager\/deletedocuments(status:)","title":"func deleteDocuments(status: DocumentStatus) async throws","type":"method"},{"path":"\/documentation\/eudiwalletkit\/storagemanager\/getdocidstotypes()","title":"func getDocIdsToTypes() -> [String : (String, DocDataFormat, String?)]","type":"method"},{"path":"\/documentation\/eudiwalletkit\/storagemanager\/getdocumentmodel(id:)","title":"func getDocumentModel(id: String) -> (any DocClaimsDecodable)?","type":"method"},{"path":"\/documentation\/eudiwalletkit\/storagemanager\/getdocumentmodels(doctype:)","title":"func getDocumentModels(docType: String) -> [any DocClaimsDecodable]","type":"method"},{"path":"\/documentation\/eudiwalletkit\/storagemanager\/loaddocument(id:uiculture:status:)","title":"func loadDocument(id: String, uiCulture: String?, status: DocumentStatus) async throws -> Document?","type":"method"},{"path":"\/documentation\/eudiwalletkit\/storagemanager\/loaddocuments(status:uiculture:)","title":"func loadDocuments(status: DocumentStatus, uiCulture: String?) async throws -> [Document]?","type":"method"},{"title":"Type Properties","type":"groupMarker"},{"path":"\/documentation\/eudiwalletkit\/storagemanager\/knowndoctypes","title":"static let knownDocTypes: [String]","type":"property"},{"title":"Type Methods","type":"groupMarker"},{"path":"\/documentation\/eudiwalletkit\/storagemanager\/tocbormdocmodel(doc:uiculture:modelfactory:)","title":"static func toCborMdocModel(doc: Document, uiCulture: String?, modelFactory: (any DocClaimsDecodableFactory)?) -> (any DocClaimsDecodable)?","type":"method"},{"path":"\/documentation\/eudiwalletkit\/storagemanager\/toclaimsmodel(doc:uiculture:modelfactory:)","title":"static func toClaimsModel(doc: Document, uiCulture: String?, modelFactory: (any DocClaimsDecodableFactory)?) -> (any DocClaimsDecodable)?","type":"method"},{"path":"\/documentation\/eudiwalletkit\/storagemanager\/tosdjwtdocmodel(doc:uiculture:modelfactory:)","title":"static func toSdJwtDocModel(doc: Document, uiCulture: String?, modelFactory: (any DocClaimsDecodableFactory)?) -> (any DocClaimsDecodable)?","type":"method"},{"title":"Default Implementations","type":"groupMarker"},{"children":[{"title":"Instance Properties","type":"groupMarker"},{"path":"\/documentation\/eudiwalletkit\/storagemanager\/objectwillchange","title":"var objectWillChange: ObservableObjectPublisher","type":"property"}],"path":"\/documentation\/eudiwalletkit\/storagemanager\/observableobject-implementations","title":"ObservableObject Implementations","type":"symbol"}],"path":"\/documentation\/eudiwalletkit\/storagemanager","title":"StorageManager","type":"class"},{"title":"Structures","type":"groupMarker"},{"children":[{"title":"Initializers","type":"groupMarker"},{"path":"\/documentation\/eudiwalletkit\/docclaimmetadata\/init(from:)","title":"init(from: any Decoder) throws","type":"init"},{"title":"Instance Properties","type":"groupMarker"},{"path":"\/documentation\/eudiwalletkit\/docclaimmetadata\/display","title":"let display: [Display]?","type":"property"},{"path":"\/documentation\/eudiwalletkit\/docclaimmetadata\/ismandatory","title":"let isMandatory: Bool?","type":"property"},{"path":"\/documentation\/eudiwalletkit\/docclaimmetadata\/valuetype","title":"let valueType: String?","type":"property"},{"title":"Instance Methods","type":"groupMarker"},{"path":"\/documentation\/eudiwalletkit\/docclaimmetadata\/getdisplayname(_:)","title":"func getDisplayName(String?) -> String?","type":"method"},{"title":"Default Implementations","type":"groupMarker"},{"children":[{"title":"Instance Methods","type":"groupMarker"},{"path":"\/documentation\/eudiwalletkit\/docclaimmetadata\/todictionary()-4lxj3","title":"func toDictionary() throws -> [String : Any]","type":"method"},{"path":"\/documentation\/eudiwalletkit\/docclaimmetadata\/todictionary()-8wear","title":"func toDictionary() throws -> [String : Any]","type":"method"}],"path":"\/documentation\/eudiwalletkit\/docclaimmetadata\/encodable-implementations","title":"Encodable Implementations","type":"symbol"}],"path":"\/documentation\/eudiwalletkit\/docclaimmetadata","title":"DocClaimMetadata","type":"struct"},{"children":[{"title":"Instance Properties","type":"groupMarker"},{"path":"\/documentation\/eudiwalletkit\/docelementsviewmodel\/displayname","title":"let displayName: String?","type":"property"},{"path":"\/documentation\/eudiwalletkit\/docelementsviewmodel\/docid","title":"var docId: String","type":"property"},{"path":"\/documentation\/eudiwalletkit\/docelementsviewmodel\/doctype","title":"let docType: String","type":"property"},{"path":"\/documentation\/eudiwalletkit\/docelementsviewmodel\/elements","title":"var elements: [ElementViewModel]","type":"property"},{"path":"\/documentation\/eudiwalletkit\/docelementsviewmodel\/id","title":"var id: String","type":"property"},{"path":"\/documentation\/eudiwalletkit\/docelementsviewmodel\/isenabled","title":"var isEnabled: Bool","type":"property"}],"path":"\/documentation\/eudiwalletkit\/docelementsviewmodel","title":"DocElementsViewModel","type":"struct"},{"children":[{"title":"Initializers","type":"groupMarker"},{"path":"\/documentation\/eudiwalletkit\/docmetadata\/init(doctype:display:namespacedclaims:flatclaims:)","title":"init(docType: String?, display: [Display]?, namespacedClaims: [NameSpace : [String : DocClaimMetadata]]?, flatClaims: [String : DocClaimMetadata]?)","type":"init"},{"path":"\/documentation\/eudiwalletkit\/docmetadata\/init(from:)-2filf","title":"init(from: any Decoder) throws","type":"init"},{"path":"\/documentation\/eudiwalletkit\/docmetadata\/init(from:)-6dd5v","title":"init?(from: Data?)","type":"init"},{"title":"Instance Properties","type":"groupMarker"},{"path":"\/documentation\/eudiwalletkit\/docmetadata\/display","title":"let display: [Display]?","type":"property"},{"path":"\/documentation\/eudiwalletkit\/docmetadata\/doctype","title":"let docType: String?","type":"property"},{"path":"\/documentation\/eudiwalletkit\/docmetadata\/flatclaims","title":"let flatClaims: [String : DocClaimMetadata]?","type":"property"},{"path":"\/documentation\/eudiwalletkit\/docmetadata\/namespacedclaims","title":"let namespacedClaims: [NameSpace : [String : DocClaimMetadata]]?","type":"property"},{"title":"Instance Methods","type":"groupMarker"},{"path":"\/documentation\/eudiwalletkit\/docmetadata\/getdisplayname(_:)","title":"func getDisplayName(String?) -> String?","type":"method"},{"path":"\/documentation\/eudiwalletkit\/docmetadata\/todata()","title":"func toData() -> Data?","type":"method"},{"title":"Default Implementations","type":"groupMarker"},{"children":[{"title":"Instance Methods","type":"groupMarker"},{"path":"\/documentation\/eudiwalletkit\/docmetadata\/todictionary()-6jrk9","title":"func toDictionary() throws -> [String : Any]","type":"method"},{"path":"\/documentation\/eudiwalletkit\/docmetadata\/todictionary()-7x571","title":"func toDictionary() throws -> [String : Any]","type":"method"}],"path":"\/documentation\/eudiwalletkit\/docmetadata\/encodable-implementations","title":"Encodable Implementations","type":"symbol"}],"path":"\/documentation\/eudiwalletkit\/docmetadata","title":"DocMetadata","type":"struct"},{"children":[{"title":"Instance Properties","type":"groupMarker"},{"path":"\/documentation\/eudiwalletkit\/elementviewmodel\/displayname","title":"let displayName: String?","type":"property"},{"path":"\/documentation\/eudiwalletkit\/elementviewmodel\/elementidentifier","title":"let elementIdentifier: String","type":"property"},{"path":"\/documentation\/eudiwalletkit\/elementviewmodel\/id","title":"var id: String","type":"property"},{"path":"\/documentation\/eudiwalletkit\/elementviewmodel\/intenttoretain","title":"let intentToRetain: Bool","type":"property"},{"path":"\/documentation\/eudiwalletkit\/elementviewmodel\/isdisabled","title":"var isDisabled: Bool","type":"property"},{"path":"\/documentation\/eudiwalletkit\/elementviewmodel\/isenabled","title":"var isEnabled: Bool","type":"property"},{"path":"\/documentation\/eudiwalletkit\/elementviewmodel\/isoptional","title":"let isOptional: Bool","type":"property"},{"path":"\/documentation\/eudiwalletkit\/elementviewmodel\/isselected","title":"var isSelected: Bool","type":"property"},{"path":"\/documentation\/eudiwalletkit\/elementviewmodel\/namespace","title":"let nameSpace: String","type":"property"}],"path":"\/documentation\/eudiwalletkit\/elementviewmodel","title":"ElementViewModel","type":"struct"},{"children":[{"title":"Instance Properties","type":"groupMarker"},{"path":"\/documentation\/eudiwalletkit\/offereddocmodel\/algvaluessupported","title":"let algValuesSupported: [String]","type":"property"},{"path":"\/documentation\/eudiwalletkit\/offereddocmodel\/credentialconfigurationidentifier","title":"let credentialConfigurationIdentifier: String","type":"property"},{"path":"\/documentation\/eudiwalletkit\/offereddocmodel\/displayname","title":"let displayName: String","type":"property"},{"path":"\/documentation\/eudiwalletkit\/offereddocmodel\/doctype","title":"let docType: String?","type":"property"},{"path":"\/documentation\/eudiwalletkit\/offereddocmodel\/doctypeorscope","title":"var docTypeOrScope: String","type":"property"},{"path":"\/documentation\/eudiwalletkit\/offereddocmodel\/scope","title":"let scope: String","type":"property"}],"path":"\/documentation\/eudiwalletkit\/offereddocmodel","title":"OfferedDocModel","type":"struct"},{"children":[{"title":"Instance Properties","type":"groupMarker"},{"path":"\/documentation\/eudiwalletkit\/offeredissuancemodel\/docmodels","title":"let docModels: [OfferedDocModel]","type":"property"},{"path":"\/documentation\/eudiwalletkit\/offeredissuancemodel\/istxcoderequired","title":"var isTxCodeRequired: Bool","type":"property"},{"path":"\/documentation\/eudiwalletkit\/offeredissuancemodel\/issuername","title":"let issuerName: String","type":"property"},{"path":"\/documentation\/eudiwalletkit\/offeredissuancemodel\/txcodespec","title":"let txCodeSpec: TxCode?","type":"property"}],"path":"\/documentation\/eudiwalletkit\/offeredissuancemodel","title":"OfferedIssuanceModel","type":"struct"},{"title":"Type Aliases","type":"groupMarker"},{"path":"\/documentation\/eudiwalletkit\/requestitems","title":"RequestItems","type":"typealias"},{"title":"Enumerations","type":"groupMarker"},{"children":[{"title":"Enumeration Cases","type":"groupMarker"},{"path":"\/documentation\/eudiwalletkit\/flowtype\/ble","title":"case ble","type":"case"},{"path":"\/documentation\/eudiwalletkit\/flowtype\/openid4vp(qrcode:)","title":"case openid4vp(qrCode: Data)","type":"case"},{"path":"\/documentation\/eudiwalletkit\/flowtype\/other","title":"case other","type":"case"},{"title":"Initializers","type":"groupMarker"},{"path":"\/documentation\/eudiwalletkit\/flowtype\/init(from:)","title":"init(from: any Decoder) throws","type":"init"},{"title":"Instance Properties","type":"groupMarker"},{"path":"\/documentation\/eudiwalletkit\/flowtype\/isproximity","title":"var isProximity: Bool","type":"property"},{"path":"\/documentation\/eudiwalletkit\/flowtype\/qrcode","title":"var qrCode: Data?","type":"property"},{"title":"Default Implementations","type":"groupMarker"},{"children":[{"title":"Instance Methods","type":"groupMarker"},{"path":"\/documentation\/eudiwalletkit\/flowtype\/todictionary()-364xh","title":"func toDictionary() throws -> [String : Any]","type":"method"},{"path":"\/documentation\/eudiwalletkit\/flowtype\/todictionary()-4h2em","title":"func toDictionary() throws -> [String : Any]","type":"method"}],"path":"\/documentation\/eudiwalletkit\/flowtype\/encodable-implementations","title":"Encodable Implementations","type":"symbol"},{"children":[{"title":"Operators","type":"groupMarker"},{"path":"\/documentation\/eudiwalletkit\/flowtype\/!=(_:_:)","title":"static func != (Self, Self) -> Bool","type":"op"}],"path":"\/documentation\/eudiwalletkit\/flowtype\/equatable-implementations","title":"Equatable Implementations","type":"symbol"}],"path":"\/documentation\/eudiwalletkit\/flowtype","title":"FlowType","type":"enum"},{"children":[{"title":"Enumeration Cases","type":"groupMarker"},{"path":"\/documentation\/eudiwalletkit\/openid4vcierror\/authrequestfailed(_:)","title":"case authRequestFailed(any Error)","type":"case"},{"path":"\/documentation\/eudiwalletkit\/openid4vcierror\/authorizeresponsenocode","title":"case authorizeResponseNoCode","type":"case"},{"path":"\/documentation\/eudiwalletkit\/openid4vcierror\/authorizeresponsenourl","title":"case authorizeResponseNoUrl","type":"case"},{"path":"\/documentation\/eudiwalletkit\/openid4vcierror\/datanotvalid","title":"case dataNotValid","type":"case"},{"path":"\/documentation\/eudiwalletkit\/openid4vcierror\/tokenrequestfailed(_:)","title":"case tokenRequestFailed(any Error)","type":"case"},{"path":"\/documentation\/eudiwalletkit\/openid4vcierror\/tokenresponseinvaliddata(_:)","title":"case tokenResponseInvalidData(String)","type":"case"},{"path":"\/documentation\/eudiwalletkit\/openid4vcierror\/tokenresponsenodata","title":"case tokenResponseNoData","type":"case"},{"title":"Instance Properties","type":"groupMarker"},{"path":"\/documentation\/eudiwalletkit\/openid4vcierror\/localizeddescription","title":"var localizedDescription: String","type":"property"},{"title":"Default Implementations","type":"groupMarker"},{"children":[{"title":"Instance Properties","type":"groupMarker"},{"path":"\/documentation\/eudiwalletkit\/openid4vcierror\/errordescription","title":"var errorDescription: String?","type":"property"},{"path":"\/documentation\/eudiwalletkit\/openid4vcierror\/failurereason","title":"var failureReason: String?","type":"property"},{"path":"\/documentation\/eudiwalletkit\/openid4vcierror\/helpanchor","title":"var helpAnchor: String?","type":"property"},{"path":"\/documentation\/eudiwalletkit\/openid4vcierror\/recoverysuggestion","title":"var recoverySuggestion: String?","type":"property"}],"path":"\/documentation\/eudiwalletkit\/openid4vcierror\/localizederror-implementations","title":"LocalizedError Implementations","type":"symbol"}],"path":"\/documentation\/eudiwalletkit\/openid4vcierror","title":"OpenId4VCIError","type":"enum"},{"children":[{"title":"Enumeration Cases","type":"groupMarker"},{"path":"\/documentation\/eudiwalletkit\/storagetype\/keychain","title":"case keyChain","type":"case"},{"title":"Default Implementations","type":"groupMarker"},{"children":[{"title":"Operators","type":"groupMarker"},{"path":"\/documentation\/eudiwalletkit\/storagetype\/!=(_:_:)","title":"static func != (Self, Self) -> Bool","type":"op"}],"path":"\/documentation\/eudiwalletkit\/storagetype\/equatable-implementations","title":"Equatable Implementations","type":"symbol"}],"path":"\/documentation\/eudiwalletkit\/storagetype","title":"StorageType","type":"enum"},{"children":[{"title":"Enumeration Cases","type":"groupMarker"},{"path":"\/documentation\/eudiwalletkit\/walleterror\/generic(_:)","title":"case generic(String)","type":"case"},{"title":"Initializers","type":"groupMarker"},{"path":"\/documentation\/eudiwalletkit\/walleterror\/init(description:userinfo:)","title":"init(description: String, userInfo: [String : Any]?)","type":"init"},{"title":"Instance Properties","type":"groupMarker"},{"path":"\/documentation\/eudiwalletkit\/walleterror\/errordescription","title":"var errorDescription: String?","type":"property"},{"title":"Default Implementations","type":"groupMarker"},{"children":[{"title":"Instance Properties","type":"groupMarker"},{"path":"\/documentation\/eudiwalletkit\/walleterror\/localizeddescription","title":"var localizedDescription: String","type":"property"}],"path":"\/documentation\/eudiwalletkit\/walleterror\/error-implementations","title":"Error Implementations","type":"symbol"},{"children":[{"title":"Instance Properties","type":"groupMarker"},{"path":"\/documentation\/eudiwalletkit\/walleterror\/failurereason","title":"var failureReason: String?","type":"property"},{"path":"\/documentation\/eudiwalletkit\/walleterror\/helpanchor","title":"var helpAnchor: String?","type":"property"},{"path":"\/documentation\/eudiwalletkit\/walleterror\/recoverysuggestion","title":"var recoverySuggestion: String?","type":"property"}],"path":"\/documentation\/eudiwalletkit\/walleterror\/localizederror-implementations","title":"LocalizedError Implementations","type":"symbol"}],"path":"\/documentation\/eudiwalletkit\/walleterror","title":"WalletError","type":"enum"},{"title":"Extended Modules","type":"groupMarker"},{"children":[{"title":"Extended Classes","type":"groupMarker"},{"children":[{"title":"Type Methods","type":"groupMarker"},{"path":"\/documentation\/eudiwalletkit\/foundation\/filemanager\/getcachesdirectory()","title":"static func getCachesDirectory() throws -> URL","type":"method"}],"path":"\/documentation\/eudiwalletkit\/foundation\/filemanager","title":"FileManager","type":"extension"},{"title":"Extended Structures","type":"groupMarker"},{"children":[{"title":"Initializers","type":"groupMarker"},{"path":"\/documentation\/eudiwalletkit\/foundation\/data\/init(base64urlencoded:)","title":"init?(base64urlEncoded: String)","type":"init"}],"path":"\/documentation\/eudiwalletkit\/foundation\/data","title":"Data","type":"extension"}],"path":"\/documentation\/eudiwalletkit\/foundation","title":"Foundation","type":"extension"},{"children":[{"title":"Extended Protocols","type":"groupMarker"},{"children":[{"title":"Type Methods","type":"groupMarker"},{"path":"\/documentation\/eudiwalletkit\/mdocdatamodel18013\/docclaimsdecodable\/extractjsonclaims(_:_:_:_:_:)","title":"static func extractJSONClaims(JSON, inout [DocClaim], [String : String]?, [String : Bool]?, [String : String]?)","type":"method"}],"path":"\/documentation\/eudiwalletkit\/mdocdatamodel18013\/docclaimsdecodable","title":"DocClaimsDecodable","type":"extension"},{"title":"Extended Structures","type":"groupMarker"},{"children":[{"title":"Type Methods","type":"groupMarker"},{"path":"\/documentation\/eudiwalletkit\/mdocdatamodel18013\/cosekeyprivate\/from(base64:)","title":"static func from(base64: String) async -> CoseKeyPrivate?","type":"method"}],"path":"\/documentation\/eudiwalletkit\/mdocdatamodel18013\/cosekeyprivate","title":"CoseKeyPrivate","type":"extension"},{"children":[{"title":"Instance Properties","type":"groupMarker"},{"path":"\/documentation\/eudiwalletkit\/mdocdatamodel18013\/signupresponse\/deviceprivatekey","title":"var devicePrivateKey: CoseKeyPrivate?","type":"property"},{"title":"Type Methods","type":"groupMarker"},{"path":"\/documentation\/eudiwalletkit\/mdocdatamodel18013\/signupresponse\/decomposecborsignupresponse(data:)","title":"static func decomposeCBORSignupResponse(data: Data) -> [(docType: String, jsonData: Data, drData: Data, issData: Data, pkData: Data)]?","type":"method"}],"path":"\/documentation\/eudiwalletkit\/mdocdatamodel18013\/signupresponse","title":"SignUpResponse","type":"extension"}],"path":"\/documentation\/eudiwalletkit\/mdocdatamodel18013","title":"MdocDataModel18013","type":"extension"},{"children":[{"title":"Extended Structures","type":"groupMarker"},{"children":[{"title":"Instance Properties","type":"groupMarker"},{"path":"\/documentation\/eudiwalletkit\/swift\/array\/items","title":"var items: RequestItems","type":"property"}],"path":"\/documentation\/eudiwalletkit\/swift\/array","title":"Array","type":"extension"},{"children":[{"title":"Instance Methods","type":"groupMarker"},{"path":"\/documentation\/eudiwalletkit\/swift\/string\/translated()","title":"func translated() -> String","type":"method"}],"path":"\/documentation\/eudiwalletkit\/swift\/string","title":"String","type":"extension"}],"path":"\/documentation\/eudiwalletkit\/swift","title":"Swift","type":"extension"},{"children":[{"title":"Extended Structures","type":"groupMarker"},{"children":[{"title":"Instance Properties","type":"groupMarker"},{"path":"\/documentation\/eudiwalletkit\/walletstorage\/document\/authorizepresentationurl","title":"var authorizePresentationUrl: String?","type":"property"},{"title":"Instance Methods","type":"groupMarker"},{"path":"\/documentation\/eudiwalletkit\/walletstorage\/document\/getdisplayname(_:)","title":"func getDisplayName(String?) -> String?","type":"method"},{"path":"\/documentation\/eudiwalletkit\/walletstorage\/document\/getdisplaynames(_:)","title":"func getDisplayNames(String?) -> [String : [String : String]]?","type":"method"}],"path":"\/documentation\/eudiwalletkit\/walletstorage\/document","title":"Document","type":"extension"}],"path":"\/documentation\/eudiwalletkit\/walletstorage","title":"WalletStorage","type":"extension"}],"path":"\/documentation\/eudiwalletkit","title":"EudiWalletKit","type":"module"}]},"schemaVersion":{"major":0,"minor":1,"patch":2}}